README.rst
setup.cfg
setup.py
peek_admin/__init__.py
peek_admin.egg-info/PKG-INFO
peek_admin.egg-info/SOURCES.txt
peek_admin.egg-info/dependency_links.txt
peek_admin.egg-info/not-zip-safe
peek_admin.egg-info/top_level.txt
peek_admin/build-web/.gitignore
peek_admin/build-web/README.md
peek_admin/build-web/angular.json
peek_admin/build-web/browserslist
peek_admin/build-web/karma.conf.js
peek_admin/build-web/package-lock.json
peek_admin/build-web/package.json
peek_admin/build-web/protractor.conf.js
peek_admin/build-web/proxy.conf.json
peek_admin/build-web/tsconfig.json
peek_admin/build-web/tslint.json
peek_admin/build-web/e2e/app.e2e-spec.ts
peek_admin/build-web/e2e/app.po.ts
peek_admin/build-web/e2e/tsconfig.e2e.json
peek_admin/build-web/src/app.module.ts
peek_admin/build-web/src/favicon.ico
peek_admin/build-web/src/index.html
peek_admin/build-web/src/main.ts
peek_admin/build-web/src/polyfills.ts
peek_admin/build-web/src/styles.scss
peek_admin/build-web/src/test.ts
peek_admin/build-web/src/tsconfig.app.json
peek_admin/build-web/src/tsconfig.spec.json
peek_admin/build-web/src/typings.d.ts
peek_admin/build-web/src/assets/.gitkeep
peek_admin/build-web/src/environments/environment.prod.ts
peek_admin/build-web/src/environments/environment.ts
peek_admin/src/app/app-routing.module.ts
peek_admin/src/app/app.component.html
peek_admin/src/app/app.component.scss
peek_admin/src/app/app.component.spec.ts
peek_admin/src/app/app.component.ts
peek_admin/src/app/index.html
peek_admin/src/app/plugin-root.component.ts
peek_admin/src/app/dashboard/dashboard.component.html
peek_admin/src/app/dashboard/dashboard.component.scss
peek_admin/src/app/dashboard/dashboard.component.spec.ts
peek_admin/src/app/dashboard/dashboard.component.ts
peek_admin/src/app/dashboard/dashboard.module.ts
peek_admin/src/app/dashboard/dashboard-stats/dashboard-stats.component.html
peek_admin/src/app/dashboard/dashboard-stats/dashboard-stats.component.scss
peek_admin/src/app/dashboard/dashboard-stats/dashboard-stats.component.spec.ts
peek_admin/src/app/dashboard/dashboard-stats/dashboard-stats.component.ts
peek_admin/src/app/navbar/navbar.component.html
